pandapower/__init__.py
pandapower/_version.py
pandapower/auxiliary.py
pandapower/build_branch.py
pandapower/build_bus.py
pandapower/build_gen.py
pandapower/convert_format.py
pandapower/file_io.py
pandapower/groups.py
pandapower/io_utils.py
pandapower/network_structure.py
pandapower/optimal_powerflow.py
pandapower/pd2ppc.py
pandapower/pd2ppc_zero.py
pandapower/powerflow.py
pandapower/pp_types.py
pandapower/results.py
pandapower/results_branch.py
pandapower/results_bus.py
pandapower/results_gen.py
pandapower/run.py
pandapower/runpm.py
pandapower/sql_io.py
pandapower/std_types.py
pandapower/contingency/__init__.py
pandapower/contingency/contingency.py
pandapower/contingency/contingency_parallel.py
pandapower/control/__init__.py
pandapower/control/basic_controller.py
pandapower/control/run_control.py
pandapower/control/controller/__init__.py
pandapower/control/controller/characteristic_control.py
pandapower/control/controller/const_control.py
pandapower/control/controller/dmr_control.py
pandapower/control/controller/pq_control.py
pandapower/control/controller/shunt_control.py
pandapower/control/controller/station_control.py
pandapower/control/controller/trafo_control.py
pandapower/control/controller/DERController/DERBasics.py
pandapower/control/controller/DERController/PQVAreas.py
pandapower/control/controller/DERController/QModels.py
pandapower/control/controller/DERController/__init__.py
pandapower/control/controller/DERController/der_control.py
pandapower/control/controller/DERController/der_control_plot.py
pandapower/control/controller/trafo/ContinuousTapControl.py
pandapower/control/controller/trafo/DiscreteTapControl.py
pandapower/control/controller/trafo/TapDependentImpedance.py
pandapower/control/controller/trafo/VmSetTapControl.py
pandapower/control/controller/trafo/__init__.py
pandapower/control/util/__init__.py
pandapower/control/util/auxiliary.py
pandapower/control/util/characteristic.py
pandapower/control/util/diagnostic.py
pandapower/converter/__init__.py
pandapower-3.3.1.dist-info/licenses/AUTHORS
pandapower-3.3.1.dist-info/licenses/LICENSE
pandapower-3.3.1.dist-info/METADATA
pandapower-3.3.1.dist-info/WHEEL
pandapower-3.3.1.dist-info/top_level.txt
pandapower-3.3.1.dist-info/RECORD
