Metadata-Version: 2.4
Name: pandapower
Version: 3.3.1
Summary: An easy to use open source tool for power system modeling, analysis and optimization with a high degree of automation.
Author-email: Leon Thurner <leon.thurner@retoflow.de>, Alexander Scheidler <alexander.scheidler@iee.fraunhofer.de>, Mike Vogt <mike.vogt@iee.fraunhofer.de>
Maintainer-email: pandapower Developers <info@pandapower.org>
Project-URL: Homepage, https://www.pandapower.org
Project-URL: Documentation, https://pandapower.readthedocs.io
Project-URL: Source, https://www.github.com/e2nIEE/pandapower
Project-URL: Repository, https://www.github.com/e2nIEE/pandapower.git
Project-URL: Issues, https://www.github.com/e2nIEE/pandapower/issues
Project-URL: Download, https://pypi.org/project/pandapower/#files
Project-URL: Changelog, https://github.com/e2nIEE/pandapower/blob/develop/CHANGELOG.rst
Keywords: power system,network,analysis,optimization,automation,grid,electricity,energy,engineering,simulation,pandapower
Classifier: Development Status :: 5 - Production/Stable
Classifier: Environment :: Console
Classifier: Intended Audience :: Developers
Classifier: Intended Audience :: Education
Classifier: Intended Audience :: Science/Research
Classifier: License :: OSI Approved :: BSD License
Classifier: Natural Language :: English
Classifier: Operating System :: OS Independent
Classifier: Programming Language :: Python
Classifier: Programming Language :: Python :: 3
Classifier: Programming Language :: Python :: 3.10
Classifier: Programming Language :: Python :: 3.11
Classifier: Programming Language :: Python :: 3.12
Classifier: Programming Language :: Python :: 3.13
Requires-Python: >=3.10
License-File: LICENSE
License-File: AUTHORS
Requires-Dist: pandas~=2.3
Requires-Dist: networkx~=3.4
Requires-Dist: scipy~=1.16.0
Requires-Dist: numpy~=2.2
Requires-Dist: packaging~=25.0
Requires-Dist: tqdm~=4.67
Requires-Dist: deepdiff~=8.6
Requires-Dist: geojson~=3.2
Requires-Dist: typing_extensions~=4.9
Requires-Dist: pandera~=0.26.1
Provides-Extra: docs
Requires-Dist: numpydoc~=1.9; extra == "docs"
Requires-Dist: matplotlib~=3.10; extra == "docs"
Requires-Dist: sphinx~=8.1; extra == "docs"
Requires-Dist: sphinx_rtd_theme~=3.0; extra == "docs"
Requires-Dist: sphinx-pyproject~=0.3; extra == "docs"
Requires-Dist: sphinxcontrib-imagesvg~=0.1; extra == "docs"
Requires-Dist: pandapower[converter]; extra == "docs"
Provides-Extra: plotting
Requires-Dist: plotly~=6.3; extra == "plotting"
Requires-Dist: matplotlib~=3.10; extra == "plotting"
Requires-Dist: igraph; extra == "plotting"
Requires-Dist: geopandas~=1.1; extra == "plotting"
Provides-Extra: test
Requires-Dist: pytest~=8.4; extra == "test"
Requires-Dist: pytest-xdist~=3.8; extra == "test"
Requires-Dist: nbmake~=1.5; extra == "test"
Provides-Extra: performance
Requires-Dist: ortools~=9.14; extra == "performance"
Requires-Dist: numba~=0.61; extra == "performance"
Requires-Dist: lightsim2grid~=0.10.3; extra == "performance"
Provides-Extra: fileio
Requires-Dist: xlsxwriter~=3.2; extra == "fileio"
Requires-Dist: openpyxl~=3.1; extra == "fileio"
Requires-Dist: cryptography~=46.0; extra == "fileio"
Requires-Dist: geopandas~=1.1; extra == "fileio"
Requires-Dist: psycopg~=3.2; extra == "fileio"
Requires-Dist: lxml~=6.0; extra == "fileio"
Provides-Extra: converter
Requires-Dist: matpowercaseframes~=1.1; extra == "converter"
Requires-Dist: lxml~=6.0; extra == "converter"
Provides-Extra: pgm
Requires-Dist: power-grid-model-io~=1.2; extra == "pgm"
Provides-Extra: control
Requires-Dist: shapely~=2.1; extra == "control"
Provides-Extra: pandamodels
Requires-Dist: juliacall~=0.9; extra == "pandamodels"
Provides-Extra: typing
Requires-Dist: mypy~=1.18; extra == "typing"
Requires-Dist: pandas-stubs~=2.3; extra == "typing"
Requires-Dist: types-shapely~=2.1; extra == "typing"
Requires-Dist: types-psycopg2~=2.9; extra == "typing"
Requires-Dist: types-openpyxl~=3.1; extra == "typing"
Requires-Dist: types-networkx~=3.4; extra == "typing"
Requires-Dist: types-tqdm~=4.67; extra == "typing"
Requires-Dist: scipy-stubs~=1.15; extra == "typing"
Requires-Dist: pandera[mypy]~=0.26.1; extra == "typing"
Provides-Extra: all
Requires-Dist: pandapower[control,converter,docs,fileio,performance,pgm,plotting,test,typing]; extra == "all"
Dynamic: license-file
